odoo/addons/sale_order_line_price_history/README.rst
odoo/addons/sale_order_line_price_history/__init__.py
odoo/addons/sale_order_line_price_history/__manifest__.py
odoo/addons/sale_order_line_price_history/i18n/de.po
odoo/addons/sale_order_line_price_history/i18n/es.po
odoo/addons/sale_order_line_price_history/i18n/it.po
odoo/addons/sale_order_line_price_history/i18n/pt.po
odoo/addons/sale_order_line_price_history/i18n/sale_order_line_price_history.pot
odoo/addons/sale_order_line_price_history/i18n/zh_CN.po
odoo/addons/sale_order_line_price_history/models/__init__.py
odoo/addons/sale_order_line_price_history/models/sale_order_line.py
odoo/addons/sale_order_line_price_history/readme/CONTRIBUTORS.rst
odoo/addons/sale_order_line_price_history/readme/DESCRIPTION.rst
odoo/addons/sale_order_line_price_history/readme/ROADMAP.rst
odoo/addons/sale_order_line_price_history/readme/USAGE.rst
odoo/addons/sale_order_line_price_history/security/ir.model.access.csv
odoo/addons/sale_order_line_price_history/static/description/icon.png
odoo/addons/sale_order_line_price_history/static/description/index.html
odoo/addons/sale_order_line_price_history/static/src/js/sale_line_price_history_widget.js
odoo/addons/sale_order_line_price_history/static/src/xml/sale_line_price_history_widget.xml
odoo/addons/sale_order_line_price_history/tests/__init__.py
odoo/addons/sale_order_line_price_history/tests/test_sale_order_line_price_history.py
odoo/addons/sale_order_line_price_history/views/assets.xml
odoo/addons/sale_order_line_price_history/views/sale_views.xml
odoo/addons/sale_order_line_price_history/wizards/__init__.py
odoo/addons/sale_order_line_price_history/wizards/sale_order_line_price_history.py
odoo/addons/sale_order_line_price_history/wizards/sale_order_line_price_history.xml
odoo14_addon_sale_order_line_price_history-14.0.1.0.1.dev12.dist-info/METADATA
odoo14_addon_sale_order_line_price_history-14.0.1.0.1.dev12.dist-info/WHEEL
odoo14_addon_sale_order_line_price_history-14.0.1.0.1.dev12.dist-info/top_level.txt
odoo14_addon_sale_order_line_price_history-14.0.1.0.1.dev12.dist-info/RECORD
